LICENSE
MANIFEST.in
README.md
setup.py
jupyter_vvp.egg-info/PKG-INFO
jupyter_vvp.egg-info/SOURCES.txt
jupyter_vvp.egg-info/dependency_links.txt
jupyter_vvp.egg-info/requires.txt
jupyter_vvp.egg-info/top_level.txt
jupytervvp/__init__.py
jupytervvp/deploymentapiconstants.py
jupytervvp/deploymentoutput.py
jupytervvp/deployments.py
jupytervvp/flinksql.py
jupytervvp/flinksqlkernel.py
jupytervvp/httpsession.py
jupytervvp/jsonconversion.py
jupytervvp/variablesubstitution.py
jupytervvp/vvpmagics.py
jupytervvp/vvpsession.py
jupytervvp/flinksqlkernel/kernel.json