Metadata-Version: 2.1
Name: jupyter-vvp
Version: 0.1.0
Summary: Jupyter VVP: Flink SQL in Jupyter Notebooks via Ververica Platform
Home-page: https://github.com/ververica/jupyter-vvp
Author: Ververica
Author-email: platform@ververica.com
License: Apache License 2.0
Download-URL: https://github.com/ververica/jupyter-vvp
Platform: UNKNOWN
